annotlib/__init__.py
annotlib/base.py
annotlib/classifier_based.py
annotlib/cluster_based.py
annotlib/difficulty_based.py
annotlib/dynamic.py
annotlib/multi_types.py
annotlib/standard.py
annotlib/utils.py
annotlib/tests/__init__.py
annotlib/tests/test_base.py
annotlib/tests/test_classifier_based.py
annotlib/tests/test_cluster_based.py
annotlib/tests/test_difficulty_based.py
annotlib/tests/test_dynamic.py
annotlib/tests/test_multiple_types.py
annotlib/tests/test_standard.py
annotlib/tests/test_utils.py
annotlib-1.0.0.dist-info/LICENSE
annotlib-1.0.0.dist-info/METADATA
annotlib-1.0.0.dist-info/WHEEL
annotlib-1.0.0.dist-info/top_level.txt
annotlib-1.0.0.dist-info/RECORD
