Metadata-Version: 2.1
Name: annotlib
Version: 1.0.0
Summary: The package annotlib is a library of techniques to simulate the labeling behaviour of real annotators.
Home-page: https://annotlib.readthedocs.io/en/latest/overview.html
Author: Marek Herde
Author-email: marek.herde@uni-kassel.de
License: MIT
Keywords: active learning machine learning annotator labeling
Platform: UNKNOWN
Classifier: License :: OSI Approved :: MIT License
Classifier: Programming Language :: Python :: 3.5
Classifier: Programming Language :: Python :: 3.6
Classifier: Programming Language :: Python :: 3.7
Classifier: Programming Language :: Python :: 3.8
Classifier: Operating System :: OS Independent
Requires-Dist: numpy
Requires-Dist: scipy
Requires-Dist: scikit-learn
Requires-Dist: matplotlib
Requires-Dist: pandas
Requires-Dist: seaborn
Requires-Dist: numpy-indexed
